src/__init__.py
src/adapters/__init__.py
src/adapters/base.py
src/adapters/browser_adapter.py
src/adapters/local_adapter.py
src/adapters/proxy_client.py
src/adapters/proxy_server.py
src/adapters/text_input_adapter.py
src/adapters/touchdesigner_adapter.py
src/adapters/touchdesigner_webrtc_adapter.py
src/adapters/touchdesigner_webrtc_proper_adapter.py
src/adapters/type.py
src/audio/__init__.py
src/audio/threads.py
src/audio/type.py
src/audio/utils/__init__.py
src/audio/utils/calculate_volume.py
src/audio/utils/has_speech_activity.py
src/audio/utils/select_audio_device.py
src/audio/utils/voice_activity_detector.py
src/config.py
src/constants.py
src/unified_app.py
src/volcengine/__init__.py
src/volcengine/client.py
src/volcengine/config.py
src/volcengine/protocol.py
volcengine_s2s_framework-0.1.0.dist-info/METADATA
volcengine_s2s_framework-0.1.0.dist-info/WHEEL
volcengine_s2s_framework-0.1.0.dist-info/RECORD
