Metadata-Version: 2.3
Name: volcengine-s2s-framework
Version: 0.1.0
Summary: 通用语音对话框架，支持多种适配器和火山引擎语音服务
License: MIT
Keywords: speech,audio,volcengine,websocket,voice
Author: markshawn2020
Author-email: shawninjuly@gmail.com
Requires-Python: >=3.11
Classifier: Development Status :: 3 - Alpha
Classifier: Intended Audience :: Developers
Classifier: License :: OSI Approved :: MIT License
Classifier: Programming Language :: Python :: 3
Classifier: Programming Language :: Python :: 3.11
Classifier: Programming Language :: Python :: 3.12
Classifier: Topic :: Multimedia :: Sound/Audio :: Speech
Classifier: Topic :: Software Development :: Libraries :: Python Modules
Requires-Dist: aiortc (>=1.13.0,<2.0.0)
Requires-Dist: av (>=14.4.0,<15.0.0)
Requires-Dist: ffmpeg-python (>=0.2.0,<0.3.0)
Requires-Dist: keyboard (>=0.13.5,<0.14.0)
Requires-Dist: numpy (>=2.3.0,<3.0.0)
Requires-Dist: pyaudio (>=0.2.14,<0.3.0)
Requires-Dist: pydantic (>=2.11.7,<3.0.0)
Requires-Dist: pydub (>=0.25.1,<0.26.0)
Requires-Dist: pygame (>=2.6.1,<3.0.0)
Requires-Dist: python-dotenv (>=1.1.0,<2.0.0)
Requires-Dist: python-socks (>=2.7.1,<3.0.0)
Requires-Dist: scipy (>=1.15.3,<2.0.0)
Requires-Dist: soundfile (>=0.13.1,<0.14.0)
Requires-Dist: typing-extensions (>=4.14.0,<5.0.0)
Requires-Dist: websockets (>=15.0.1,<16.0.0)
